{
   "style" : "Medium Swing",
   "metadata" : [
      "IREALB;In Your Own Sweet Way;Brubeck Dave;Medium Swing;Eb",
      "{A:T44Ah7 D7b9 |G-7 C7 |C-7 F7 |Bb7 Eb^7 |Ab-7 Db7 |Gb^7 B^7 |F7alt B7 |Bb7 Eb6 ",
      "B:E-7 A7 |D^7   |E-7 A7 |D^7   |D-7 G7 |E-7 A7 |Dh7 Ab7 |G7 C-7 ",
      "A:Ah7 D7b9 |G-7 C7 |C-7 F7 |Bb7 Eb^7 |Ab-7 Db7 |Gb^7 B^7 |F7alt B7 |Bb7 Eb6 ",
      "C:Ab7sus(Eb-7)   |%   |%   |%   |Ab7sus(Eb-7)   |%   |%   |%   "
   ],
   "title" : "In Your Own Sweet Way",
   "sections" : [
      {
         "bars" : [
            {
               "meter" : "4/4",
               "chords" : [
                  {
                     "beats" : 2,
                     "name" : "Ah7"
                  },
                  {
                     "beats" : 2,
                     "name" : "D7(b9)"
                  }
               ]
            },
            {
               "chords" : [
                  {
                     "beats" : 2,
                     "name" : "G-7"
                  },
                  {
                     "beats" : 2,
                     "name" : "C7"
                  }
               ]
            },
            {
               "chords" : [
                  {
                     "beats" : 2,
                     "name" : "C-7"
                  },
                  {
                     "beats" : 2,
                     "name" : "F7"
                  }
               ]
            },
            {
               "chords" : [
                  {
                     "beats" : 2,
                     "name" : "Bb7"
                  },
                  {
                     "beats" : 2,
                     "name" : "Eb^7"
                  }
               ]
            },
            {
               "chords" : [
                  {
                     "beats" : 2,
                     "name" : "Ab-7"
                  },
                  {
                     "beats" : 2,
                     "name" : "Db7"
                  }
               ]
            },
            {
               "chords" : [
                  {
                     "beats" : 2,
                     "name" : "Gb^7"
                  },
                  {
                     "beats" : 2,
                     "name" : "B^7"
                  }
               ]
            },
            {
               "chords" : [
                  {
                     "beats" : 2,
                     "name" : "F7alt"
                  },
                  {
                     "beats" : 2,
                     "name" : "B7"
                  }
               ]
            },
            {
               "chords" : [
                  {
                     "beats" : 2,
                     "name" : "Bb7"
                  },
                  {
                     "beats" : 2,
                     "name" : "Eb6"
                  }
               ]
            }
         ],
         "label" : "A",
         "repeat" : 1
      },
      {
         "bars" : [
            {
               "chords" : [
                  {
                     "beats" : 2,
                     "name" : "E-7"
                  },
                  {
                     "beats" : 2,
                     "name" : "A7"
                  }
               ]
            },
            {
               "chords" : [
                  {
                     "name" : "D^7"
                  }
               ]
            },
            {
               "chords" : [
                  {
                     "beats" : 2,
                     "name" : "E-7"
                  },
                  {
                     "beats" : 2,
                     "name" : "A7"
                  }
               ]
            },
            {
               "chords" : [
                  {
                     "name" : "D^7"
                  }
               ]
            },
            {
               "chords" : [
                  {
                     "beats" : 2,
                     "name" : "D-7"
                  },
                  {
                     "beats" : 2,
                     "name" : "G7"
                  }
               ]
            },
            {
               "chords" : [
                  {
                     "beats" : 2,
                     "name" : "E-7"
                  },
                  {
                     "beats" : 2,
                     "name" : "A7"
                  }
               ]
            },
            {
               "chords" : [
                  {
                     "beats" : 2,
                     "name" : "Dh7"
                  },
                  {
                     "beats" : 2,
                     "name" : "Ab7"
                  }
               ]
            },
            {
               "chords" : [
                  {
                     "beats" : 2,
                     "name" : "G7"
                  },
                  {
                     "beats" : 2,
                     "name" : "C-7"
                  }
               ]
            }
         ],
         "label" : "B"
      },
      {
         "bars" : [
            {
               "chords" : [
                  {
                     "beats" : 2,
                     "name" : "Ah7"
                  },
                  {
                     "beats" : 2,
                     "name" : "D7(b9)"
                  }
               ]
            },
            {
               "chords" : [
                  {
                     "beats" : 2,
                     "name" : "G-7"
                  },
                  {
                     "beats" : 2,
                     "name" : "C7"
                  }
               ]
            },
            {
               "chords" : [
                  {
                     "beats" : 2,
                     "name" : "C-7"
                  },
                  {
                     "beats" : 2,
                     "name" : "F7"
                  }
               ]
            },
            {
               "chords" : [
                  {
                     "beats" : 2,
                     "name" : "Bb7"
                  },
                  {
                     "beats" : 2,
                     "name" : "Eb^7"
                  }
               ]
            },
            {
               "chords" : [
                  {
                     "beats" : 2,
                     "name" : "Ab-7"
                  },
                  {
                     "beats" : 2,
                     "name" : "Db7"
                  }
               ]
            },
            {
               "chords" : [
                  {
                     "beats" : 2,
                     "name" : "Gb^7"
                  },
                  {
                     "beats" : 2,
                     "name" : "B^7"
                  }
               ]
            },
            {
               "chords" : [
                  {
                     "beats" : 2,
                     "name" : "F7alt"
                  },
                  {
                     "beats" : 2,
                     "name" : "B7"
                  }
               ]
            },
            {
               "chords" : [
                  {
                     "beats" : 2,
                     "name" : "Bb7"
                  },
                  {
                     "beats" : 2,
                     "name" : "Eb6"
                  }
               ]
            }
         ],
         "label" : "A"
      },
      {
         "bars" : [
            {
               "chords" : [
                  {
                     "altname" : "Eb-7",
                     "name" : "Ab7sus"
                  }
               ]
            },
            {
               "repeat_last" : 1
            },
            {
               "repeat_last" : 1
            },
            {
               "repeat_last" : 1
            },
            {
               "chords" : [
                  {
                     "altname" : "Eb-7",
                     "name" : "Ab7sus"
                  }
               ]
            },
            {
               "repeat_last" : 1
            },
            {
               "repeat_last" : 1
            },
            {
               "repeat_last" : 1
            }
         ],
         "label" : "C"
      }
   ],
   "composer" : "Dave Brubeck",
   "key" : "Eb"
}
