{
   "style" : "Latin",
   "metadata" : [
      "IREALB;Zoltan;Shaw Woody;Latin;C",
      "{A:T44C^7#11   |%   |%   |%   |Bb^7#11   |%   |%   |%   ",
      "B:Gb^7#11   |%   |%   |F^7#11   |Eb^7#11   |%   |Eb^7#11 F^7#11 |Ab^7#11 Bb^7#11 ",
      "A:C^7#11   |%   |%   |%   |Bb^7#11   |%   |%   |%   "
   ],
   "title" : "Zoltan",
   "sections" : [
      {
         "bars" : [
            {
               "meter" : "4/4",
               "chords" : [
                  {
                     "name" : "C^7(#11)"
                  }
               ]
            },
            {
               "repeat_last" : 1
            },
            {
               "repeat_last" : 1
            },
            {
               "repeat_last" : 1
            },
            {
               "chords" : [
                  {
                     "name" : "Bb^7(#11)"
                  }
               ]
            },
            {
               "repeat_last" : 1
            },
            {
               "repeat_last" : 1
            },
            {
               "repeat_last" : 1
            }
         ],
         "label" : "A",
         "repeat" : 1
      },
      {
         "bars" : [
            {
               "chords" : [
                  {
                     "name" : "Gb^7(#11)"
                  }
               ]
            },
            {
               "repeat_last" : 1
            },
            {
               "repeat_last" : 1
            },
            {
               "chords" : [
                  {
                     "name" : "F^7(#11)"
                  }
               ]
            },
            {
               "chords" : [
                  {
                     "name" : "Eb^7(#11)"
                  }
               ]
            },
            {
               "repeat_last" : 1
            },
            {
               "chords" : [
                  {
                     "beats" : 2,
                     "name" : "Eb^7(#11)"
                  },
                  {
                     "beats" : 2,
                     "name" : "F^7(#11)"
                  }
               ]
            },
            {
               "chords" : [
                  {
                     "beats" : 2,
                     "name" : "Ab^7(#11)"
                  },
                  {
                     "beats" : 2,
                     "name" : "Bb^7(#11)"
                  }
               ]
            }
         ],
         "label" : "B"
      },
      {
         "bars" : [
            {
               "chords" : [
                  {
                     "name" : "C^7(#11)"
                  }
               ]
            },
            {
               "repeat_last" : 1
            },
            {
               "repeat_last" : 1
            },
            {
               "repeat_last" : 1
            },
            {
               "chords" : [
                  {
                     "name" : "Bb^7(#11)"
                  }
               ]
            },
            {
               "repeat_last" : 1
            },
            {
               "repeat_last" : 1
            },
            {
               "repeat_last" : 1
            }
         ],
         "label" : "A"
      }
   ],
   "composer" : "Woody Shaw",
   "key" : "C"
}
