{
   "style" : null,
   "metadata" : [
      "IREALB;Bye Bye Baby;Styne Jule;Medium Swing;Bb",
      "A:Bb^7 A7 |Ab9 G7 |C-7   |F7   |Bb^7 Bbo7 |Bb^7 D7#5 |Eb6   |F7/Eb   ",
      "B:Bb^7/F D7/F# |G-7 Bb7/Ab |Eb^7/Bb Bo7 |C-7   |F9   |F7 F7/Eb |D-7 G7 |C-7 F7 ",
      "A:Bb^7 A7 |Ab9 G7 |C-7   |F7   |Bb^7 Bbo7 |Bb^7 G-7 |A-7   |D7   ",
      "C:G-7 Gbo7 |F-7 Bb9 |Eb^7   |Eo7   |Bb/F Gb7 |F7 F7/Eb |Dh7 Ab9#11 |G7 G7#5 |C-7   |C-7 F13b9 |Bb69   |C-7 F7 "
   ],
   "title" : "Bye Bye Baby",
   "sections" : [
      {
         "bars" : [
            {
               "chords" : [
                  {
                     "beats" : 2,
                     "name" : "Bb^7"
                  },
                  {
                     "beats" : 2,
                     "name" : "A7"
                  }
               ]
            },
            {
               "chords" : [
                  {
                     "beats" : 2,
                     "name" : "Ab9"
                  },
                  {
                     "beats" : 2,
                     "name" : "G7"
                  }
               ]
            },
            {
               "chords" : [
                  {
                     "name" : "C-7"
                  }
               ]
            },
            {
               "chords" : [
                  {
                     "name" : "F7"
                  }
               ]
            },
            {
               "chords" : [
                  {
                     "beats" : 2,
                     "name" : "Bb^7"
                  },
                  {
                     "beats" : 2,
                     "name" : "Bbo7"
                  }
               ]
            },
            {
               "chords" : [
                  {
                     "beats" : 2,
                     "name" : "Bb^7"
                  },
                  {
                     "beats" : 2,
                     "name" : "D7(#5)"
                  }
               ]
            },
            {
               "chords" : [
                  {
                     "name" : "Eb6"
                  }
               ]
            },
            {
               "chords" : [
                  {
                     "name" : "F7/E(b)"
                  }
               ]
            }
         ],
         "label" : "A"
      },
      {
         "bars" : [
            {
               "chords" : [
                  {
                     "beats" : 2,
                     "name" : "Bb^7/F"
                  },
                  {
                     "beats" : 2,
                     "name" : "D7/F(#)"
                  }
               ]
            },
            {
               "chords" : [
                  {
                     "beats" : 2,
                     "name" : "G-7"
                  },
                  {
                     "beats" : 2,
                     "name" : "Bb7/A(b)"
                  }
               ]
            },
            {
               "chords" : [
                  {
                     "beats" : 2,
                     "name" : "Eb^7/B(b)"
                  },
                  {
                     "beats" : 2,
                     "name" : "Bo7"
                  }
               ]
            },
            {
               "chords" : [
                  {
                     "name" : "C-7"
                  }
               ]
            },
            {
               "chords" : [
                  {
                     "name" : "F9"
                  }
               ]
            },
            {
               "chords" : [
                  {
                     "beats" : 2,
                     "name" : "F7"
                  },
                  {
                     "beats" : 2,
                     "name" : "F7/E(b)"
                  }
               ]
            },
            {
               "chords" : [
                  {
                     "beats" : 2,
                     "name" : "D-7"
                  },
                  {
                     "beats" : 2,
                     "name" : "G7"
                  }
               ]
            },
            {
               "chords" : [
                  {
                     "beats" : 2,
                     "name" : "C-7"
                  },
                  {
                     "beats" : 2,
                     "name" : "F7"
                  }
               ]
            }
         ],
         "label" : "B"
      },
      {
         "bars" : [
            {
               "chords" : [
                  {
                     "beats" : 2,
                     "name" : "Bb^7"
                  },
                  {
                     "beats" : 2,
                     "name" : "A7"
                  }
               ]
            },
            {
               "chords" : [
                  {
                     "beats" : 2,
                     "name" : "Ab9"
                  },
                  {
                     "beats" : 2,
                     "name" : "G7"
                  }
               ]
            },
            {
               "chords" : [
                  {
                     "name" : "C-7"
                  }
               ]
            },
            {
               "chords" : [
                  {
                     "name" : "F7"
                  }
               ]
            },
            {
               "chords" : [
                  {
                     "beats" : 2,
                     "name" : "Bb^7"
                  },
                  {
                     "beats" : 2,
                     "name" : "Bbo7"
                  }
               ]
            },
            {
               "chords" : [
                  {
                     "beats" : 2,
                     "name" : "Bb^7"
                  },
                  {
                     "beats" : 2,
                     "name" : "G-7"
                  }
               ]
            },
            {
               "chords" : [
                  {
                     "name" : "A-7"
                  }
               ]
            },
            {
               "chords" : [
                  {
                     "name" : "D7"
                  }
               ]
            }
         ],
         "label" : "A"
      },
      {
         "bars" : [
            {
               "chords" : [
                  {
                     "beats" : 2,
                     "name" : "G-7"
                  },
                  {
                     "beats" : 2,
                     "name" : "Gbo7"
                  }
               ]
            },
            {
               "chords" : [
                  {
                     "beats" : 2,
                     "name" : "F-7"
                  },
                  {
                     "beats" : 2,
                     "name" : "Bb9"
                  }
               ]
            },
            {
               "chords" : [
                  {
                     "name" : "Eb^7"
                  }
               ]
            },
            {
               "chords" : [
                  {
                     "name" : "Eo7"
                  }
               ]
            },
            {
               "chords" : [
                  {
                     "beats" : 2,
                     "name" : "Bb/F"
                  },
                  {
                     "beats" : 2,
                     "name" : "Gb7"
                  }
               ]
            },
            {
               "chords" : [
                  {
                     "beats" : 2,
                     "name" : "F7"
                  },
                  {
                     "beats" : 2,
                     "name" : "F7/E(b)"
                  }
               ]
            },
            {
               "chords" : [
                  {
                     "beats" : 2,
                     "name" : "Dh7"
                  },
                  {
                     "beats" : 2,
                     "name" : "Ab9(#11)"
                  }
               ]
            },
            {
               "chords" : [
                  {
                     "beats" : 2,
                     "name" : "G7"
                  },
                  {
                     "beats" : 2,
                     "name" : "G7(#5)"
                  }
               ]
            },
            {
               "chords" : [
                  {
                     "name" : "C-7"
                  }
               ]
            },
            {
               "chords" : [
                  {
                     "beats" : 2,
                     "name" : "C-7"
                  },
                  {
                     "beats" : 2,
                     "name" : "F13(b9)"
                  }
               ]
            },
            {
               "chords" : [
                  {
                     "name" : "Bb69"
                  }
               ]
            },
            {
               "chords" : [
                  {
                     "beats" : 2,
                     "name" : "C-7"
                  },
                  {
                     "beats" : 2,
                     "name" : "F7"
                  }
               ]
            }
         ],
         "label" : "C"
      }
   ],
   "composer" : "Jule Styne",
   "key" : null
}
