{
   "style" : "Medium Up Swing",
   "metadata" : [
      "IREALB;Hello Young Lovers;Rogers Richard;Medium Up Swing;C",
      "{T34A:C^7 |D-7 |E-7 |D-7 |C^7 |C#o7 |D-7 |G7 |Dh7 |G7/B |Eb^7/Bb |G7 |D-7 |G7 ",
      "\t1.C6 |G7 ",
      "\t2.C6 |C7 ",
      "B:F6 |G-7 |A-7 |G-7 |F^7 |G-7 |F^7 |% |Bh7 |E7 |A-7 |D7 |D-7 |A7 |D-7 |G7 ",
      "A:C^7 |D-7 |E-7 |D-7 |C^7 |C#o7 |D-7 |G7 |Dh7 |G7/B |Eb^7/Bb |G7 |D-7 |G7 |G-7 |C7 |F6 |F-7 |E7 |A7 |D-7 |Ab7,G7,|C6 |% "
   ],
   "title" : "Hello Young Lovers",
   "sections" : [
      {
         "endings" : [
            {
               "bars" : [
                  {
                     "chords" : [
                        {
                           "name" : "C6"
                        }
                     ]
                  },
                  {
                     "chords" : [
                        {
                           "name" : "G7"
                        }
                     ]
                  }
               ],
               "no" : "1"
            },
            {
               "bars" : [
                  {
                     "chords" : [
                        {
                           "name" : "C6"
                        }
                     ]
                  },
                  {
                     "chords" : [
                        {
                           "name" : "C7"
                        }
                     ]
                  }
               ],
               "no" : "2"
            }
         ],
         "bars" : [
            {
               "meter" : "3/4",
               "chords" : [
                  {
                     "name" : "C^7"
                  }
               ]
            },
            {
               "chords" : [
                  {
                     "name" : "D-7"
                  }
               ]
            },
            {
               "chords" : [
                  {
                     "name" : "E-7"
                  }
               ]
            },
            {
               "chords" : [
                  {
                     "name" : "D-7"
                  }
               ]
            },
            {
               "chords" : [
                  {
                     "name" : "C^7"
                  }
               ]
            },
            {
               "chords" : [
                  {
                     "name" : "C#o7"
                  }
               ]
            },
            {
               "chords" : [
                  {
                     "name" : "D-7"
                  }
               ]
            },
            {
               "chords" : [
                  {
                     "name" : "G7"
                  }
               ]
            },
            {
               "chords" : [
                  {
                     "name" : "Dh7"
                  }
               ]
            },
            {
               "chords" : [
                  {
                     "bass" : "B",
                     "name" : "G7"
                  }
               ]
            },
            {
               "chords" : [
                  {
                     "bass" : "Bb",
                     "name" : "Eb^7"
                  }
               ]
            },
            {
               "chords" : [
                  {
                     "name" : "G7"
                  }
               ]
            },
            {
               "chords" : [
                  {
                     "name" : "D-7"
                  }
               ]
            },
            {
               "chords" : [
                  {
                     "name" : "G7"
                  }
               ]
            }
         ],
         "label" : "A",
         "repeat" : 1
      },
      {
         "bars" : [
            {
               "chords" : [
                  {
                     "name" : "F6"
                  }
               ]
            },
            {
               "chords" : [
                  {
                     "name" : "G-7"
                  }
               ]
            },
            {
               "chords" : [
                  {
                     "name" : "A-7"
                  }
               ]
            },
            {
               "chords" : [
                  {
                     "name" : "G-7"
                  }
               ]
            },
            {
               "chords" : [
                  {
                     "name" : "F^7"
                  }
               ]
            },
            {
               "chords" : [
                  {
                     "name" : "G-7"
                  }
               ]
            },
            {
               "chords" : [
                  {
                     "name" : "F^7"
                  }
               ]
            },
            {
               "repeat_last" : 1
            },
            {
               "chords" : [
                  {
                     "name" : "Bh7"
                  }
               ]
            },
            {
               "chords" : [
                  {
                     "name" : "E7"
                  }
               ]
            },
            {
               "chords" : [
                  {
                     "name" : "A-7"
                  }
               ]
            },
            {
               "chords" : [
                  {
                     "name" : "D7"
                  }
               ]
            },
            {
               "chords" : [
                  {
                     "name" : "D-7"
                  }
               ]
            },
            {
               "chords" : [
                  {
                     "name" : "A7"
                  }
               ]
            },
            {
               "chords" : [
                  {
                     "name" : "D-7"
                  }
               ]
            },
            {
               "chords" : [
                  {
                     "name" : "G7"
                  }
               ]
            }
         ],
         "label" : "B"
      },
      {
         "bars" : [
            {
               "chords" : [
                  {
                     "name" : "C^7"
                  }
               ]
            },
            {
               "chords" : [
                  {
                     "name" : "D-7"
                  }
               ]
            },
            {
               "chords" : [
                  {
                     "name" : "E-7"
                  }
               ]
            },
            {
               "chords" : [
                  {
                     "name" : "D-7"
                  }
               ]
            },
            {
               "chords" : [
                  {
                     "name" : "C^7"
                  }
               ]
            },
            {
               "chords" : [
                  {
                     "name" : "C#o7"
                  }
               ]
            },
            {
               "chords" : [
                  {
                     "name" : "D-7"
                  }
               ]
            },
            {
               "chords" : [
                  {
                     "name" : "G7"
                  }
               ]
            },
            {
               "chords" : [
                  {
                     "name" : "Dh7"
                  }
               ]
            },
            {
               "chords" : [
                  {
                     "bass" : "B",
                     "name" : "G7"
                  }
               ]
            },
            {
               "chords" : [
                  {
                     "bass" : "Bb",
                     "name" : "Eb^7"
                  }
               ]
            },
            {
               "chords" : [
                  {
                     "name" : "G7"
                  }
               ]
            },
            {
               "chords" : [
                  {
                     "name" : "D-7"
                  }
               ]
            },
            {
               "chords" : [
                  {
                     "name" : "G7"
                  }
               ]
            },
            {
               "chords" : [
                  {
                     "name" : "G-7"
                  }
               ]
            },
            {
               "chords" : [
                  {
                     "name" : "C7"
                  }
               ]
            },
            {
               "chords" : [
                  {
                     "name" : "F6"
                  }
               ]
            },
            {
               "chords" : [
                  {
                     "name" : "F-7"
                  }
               ]
            },
            {
               "chords" : [
                  {
                     "name" : "E7"
                  }
               ]
            },
            {
               "chords" : [
                  {
                     "name" : "A7"
                  }
               ]
            },
            {
               "chords" : [
                  {
                     "name" : "D-7"
                  }
               ]
            },
            {
               "chords" : [
                  {
                     "beats" : 0.666666666666667,
                     "name" : "Ab7"
                  },
                  {
                     "beats" : 0.666666666666667,
                     "name" : "G7"
                  }
               ]
            },
            {
               "chords" : [
                  {
                     "name" : "C6"
                  }
               ]
            },
            {
               "repeat_last" : 1
            }
         ],
         "label" : "A"
      }
   ],
   "composer" : "Rogers Richard",
   "key" : "C"
}
