{
   "style" : "Ballad",
   "metadata" : [
      "IREALB;I Can't Get Started;Duke Vernon;Ballad;C",
      "{A:T44C^7 A-7 |D-7 G7 |B-7,E7,Bb-7,Eb7,|A-7,D7,Ab-7,Db7,|C^7 A-7 |D-7 G7b9 ",
      "\t1.E7 A7 |D7 G7 ",
      "\t2.C^7   |%   ",
      "B:E-7 A7 |E-7 A7 |D^7   |%   |D-7 G7 |D-7 G7 |E-7 Ebo7 |D-7 G7sus ",
      "A:C^7 A-7 |D-7 G7 |B-7,E7,Bb-7,Eb7,|A-7,D7,Ab-7,Db7,|C^7 A7#5 |D-7 G7 |C6 A7 |D7 G7 "
   ],
   "title" : "I Can't Get Started",
   "sections" : [
      {
         "endings" : [
            {
               "bars" : [
                  {
                     "chords" : [
                        {
                           "beats" : 2,
                           "name" : "E7"
                        },
                        {
                           "beats" : 2,
                           "name" : "A7"
                        }
                     ]
                  },
                  {
                     "chords" : [
                        {
                           "beats" : 2,
                           "name" : "D7"
                        },
                        {
                           "beats" : 2,
                           "name" : "G7"
                        }
                     ]
                  }
               ],
               "no" : "1"
            },
            {
               "bars" : [
                  {
                     "chords" : [
                        {
                           "name" : "C^7"
                        }
                     ]
                  },
                  {
                     "repeat_last" : 1
                  }
               ],
               "no" : "2"
            }
         ],
         "bars" : [
            {
               "meter" : "4/4",
               "chords" : [
                  {
                     "beats" : 2,
                     "name" : "C^7"
                  },
                  {
                     "beats" : 2,
                     "name" : "A-7"
                  }
               ]
            },
            {
               "chords" : [
                  {
                     "beats" : 2,
                     "name" : "D-7"
                  },
                  {
                     "beats" : 2,
                     "name" : "G7"
                  }
               ]
            },
            {
               "chords" : [
                  {
                     "beats" : 1,
                     "name" : "B-7"
                  },
                  {
                     "beats" : 1,
                     "name" : "E7"
                  },
                  {
                     "beats" : 1,
                     "name" : "Bb-7"
                  },
                  {
                     "beats" : 1,
                     "name" : "Eb7"
                  }
               ]
            },
            {
               "chords" : [
                  {
                     "beats" : 1,
                     "name" : "A-7"
                  },
                  {
                     "beats" : 1,
                     "name" : "D7"
                  },
                  {
                     "beats" : 1,
                     "name" : "Ab-7"
                  },
                  {
                     "beats" : 1,
                     "name" : "Db7"
                  }
               ]
            },
            {
               "chords" : [
                  {
                     "beats" : 2,
                     "name" : "C^7"
                  },
                  {
                     "beats" : 2,
                     "name" : "A-7"
                  }
               ]
            },
            {
               "chords" : [
                  {
                     "beats" : 2,
                     "name" : "D-7"
                  },
                  {
                     "beats" : 2,
                     "name" : "G7b9"
                  }
               ]
            }
         ],
         "label" : "A",
         "repeat" : 1
      },
      {
         "bars" : [
            {
               "chords" : [
                  {
                     "beats" : 2,
                     "name" : "E-7"
                  },
                  {
                     "beats" : 2,
                     "name" : "A7"
                  }
               ]
            },
            {
               "chords" : [
                  {
                     "beats" : 2,
                     "name" : "E-7"
                  },
                  {
                     "beats" : 2,
                     "name" : "A7"
                  }
               ]
            },
            {
               "chords" : [
                  {
                     "name" : "D^7"
                  }
               ]
            },
            {
               "repeat_last" : 1
            },
            {
               "chords" : [
                  {
                     "beats" : 2,
                     "name" : "D-7"
                  },
                  {
                     "beats" : 2,
                     "name" : "G7"
                  }
               ]
            },
            {
               "chords" : [
                  {
                     "beats" : 2,
                     "name" : "D-7"
                  },
                  {
                     "beats" : 2,
                     "name" : "G7"
                  }
               ]
            },
            {
               "chords" : [
                  {
                     "beats" : 2,
                     "name" : "E-7"
                  },
                  {
                     "beats" : 2,
                     "name" : "Ebo7"
                  }
               ]
            },
            {
               "chords" : [
                  {
                     "beats" : 2,
                     "name" : "D-7"
                  },
                  {
                     "beats" : 2,
                     "name" : "G7sus"
                  }
               ]
            }
         ],
         "label" : "B"
      },
      {
         "bars" : [
            {
               "chords" : [
                  {
                     "beats" : 2,
                     "name" : "C^7"
                  },
                  {
                     "beats" : 2,
                     "name" : "A-7"
                  }
               ]
            },
            {
               "chords" : [
                  {
                     "beats" : 2,
                     "name" : "D-7"
                  },
                  {
                     "beats" : 2,
                     "name" : "G7"
                  }
               ]
            },
            {
               "chords" : [
                  {
                     "beats" : 1,
                     "name" : "B-7"
                  },
                  {
                     "beats" : 1,
                     "name" : "E7"
                  },
                  {
                     "beats" : 1,
                     "name" : "Bb-7"
                  },
                  {
                     "beats" : 1,
                     "name" : "Eb7"
                  }
               ]
            },
            {
               "chords" : [
                  {
                     "beats" : 1,
                     "name" : "A-7"
                  },
                  {
                     "beats" : 1,
                     "name" : "D7"
                  },
                  {
                     "beats" : 1,
                     "name" : "Ab-7"
                  },
                  {
                     "beats" : 1,
                     "name" : "Db7"
                  }
               ]
            },
            {
               "chords" : [
                  {
                     "beats" : 2,
                     "name" : "C^7"
                  },
                  {
                     "beats" : 2,
                     "name" : "A7#5"
                  }
               ]
            },
            {
               "chords" : [
                  {
                     "beats" : 2,
                     "name" : "D-7"
                  },
                  {
                     "beats" : 2,
                     "name" : "G7"
                  }
               ]
            },
            {
               "chords" : [
                  {
                     "beats" : 2,
                     "name" : "C6"
                  },
                  {
                     "beats" : 2,
                     "name" : "A7"
                  }
               ]
            },
            {
               "chords" : [
                  {
                     "beats" : 2,
                     "name" : "D7"
                  },
                  {
                     "beats" : 2,
                     "name" : "G7"
                  }
               ]
            }
         ],
         "label" : "A"
      }
   ],
   "composer" : "Duke Vernon",
   "key" : "C"
}
