{
   "style" : null,
   "metadata" : [
      "IREALB;Speak Like A Child;Hancock Herbie;Bossa Nova;A-",
      "T44A:C#7alt,   |%   |G#7alt,   |E9sus, A-7 |Bb13,   |Bb7#5,   |Bb-9,   |Eb13,   |Ab13sus,   |Ab13sus, Ab13b9, |G7alt,   |%   |Gb^7#11,   |%   |Gbo7   |%   |Eb9sus,   |Eb13,   |Eb-9,   |D7#9,   |Db7alt, C7 |F^7 Bb-9, ",
      "{A-9,   |E9sus,<UmVwZWF0IDN4>   ",
      "B:C#7alt,   |%   |G#7alt,   |E9sus, A-7 |Bb13,   |Bb7#5,   |A7#9#5,   |A13b9,   |Ab13,   |Ab13b9,   |G7alt,   |%   |Gb^7#11,   |%   |Gbo7   |%   |C/Db, Bb/C, |C/B, Bb-7 ",
      "{<T3Blbg==>A-9,   |<RC5DLiBvbiBjdWU=>E9sus,   "
   ],
   "title" : "Speak Like A Child",
   "sections" : [
      {
         "bars" : [
            {
               "meter" : "4/4",
               "chords" : [
                  {
                     "name" : "C#7alt"
                  }
               ]
            },
            {
               "repeat_last" : 1
            },
            {
               "chords" : [
                  {
                     "name" : "G#7alt"
                  }
               ]
            },
            {
               "chords" : [
                  {
                     "beats" : 2,
                     "name" : "E9sus"
                  },
                  {
                     "beats" : 2,
                     "name" : "A-7"
                  }
               ]
            },
            {
               "chords" : [
                  {
                     "name" : "Bb13"
                  }
               ]
            },
            {
               "chords" : [
                  {
                     "name" : "Bb7(#5)"
                  }
               ]
            },
            {
               "chords" : [
                  {
                     "name" : "Bb-9"
                  }
               ]
            },
            {
               "chords" : [
                  {
                     "name" : "Eb13"
                  }
               ]
            },
            {
               "chords" : [
                  {
                     "name" : "Ab13sus"
                  }
               ]
            },
            {
               "chords" : [
                  {
                     "beats" : 2,
                     "name" : "Ab13sus"
                  },
                  {
                     "beats" : 2,
                     "name" : "Ab13(b9)"
                  }
               ]
            },
            {
               "chords" : [
                  {
                     "name" : "G7alt"
                  }
               ]
            },
            {
               "repeat_last" : 1
            },
            {
               "chords" : [
                  {
                     "name" : "Gb^7(#11)"
                  }
               ]
            },
            {
               "repeat_last" : 1
            },
            {
               "chords" : [
                  {
                     "name" : "Gbo7"
                  }
               ]
            },
            {
               "repeat_last" : 1
            },
            {
               "chords" : [
                  {
                     "name" : "Eb9sus"
                  }
               ]
            },
            {
               "chords" : [
                  {
                     "name" : "Eb13"
                  }
               ]
            },
            {
               "chords" : [
                  {
                     "name" : "Eb-9"
                  }
               ]
            },
            {
               "chords" : [
                  {
                     "name" : "D7(#9)"
                  }
               ]
            },
            {
               "chords" : [
                  {
                     "beats" : 2,
                     "name" : "Db7alt"
                  },
                  {
                     "beats" : 2,
                     "name" : "C7"
                  }
               ]
            },
            {
               "chords" : [
                  {
                     "beats" : 2,
                     "name" : "F^7"
                  },
                  {
                     "beats" : 2,
                     "name" : "Bb-9"
                  }
               ]
            }
         ],
         "label" : "A"
      },
      {
         "bars" : [
            {
               "chords" : [
                  {
                     "name" : "A-9"
                  }
               ]
            },
            {
               "chords" : [
                  {
                     "name" : "E9sus"
                  }
               ],
               "comments" : [
                  "0-Repeat 3x"
               ]
            }
         ],
         "repeat" : 1
      },
      {
         "bars" : [
            {
               "chords" : [
                  {
                     "name" : "C#7alt"
                  }
               ]
            },
            {
               "repeat_last" : 1
            },
            {
               "chords" : [
                  {
                     "name" : "G#7alt"
                  }
               ]
            },
            {
               "chords" : [
                  {
                     "beats" : 2,
                     "name" : "E9sus"
                  },
                  {
                     "beats" : 2,
                     "name" : "A-7"
                  }
               ]
            },
            {
               "chords" : [
                  {
                     "name" : "Bb13"
                  }
               ]
            },
            {
               "chords" : [
                  {
                     "name" : "Bb7(#5)"
                  }
               ]
            },
            {
               "chords" : [
                  {
                     "name" : "A7(#9#5)"
                  }
               ]
            },
            {
               "chords" : [
                  {
                     "name" : "A13(b9)"
                  }
               ]
            },
            {
               "chords" : [
                  {
                     "name" : "Ab13"
                  }
               ]
            },
            {
               "chords" : [
                  {
                     "name" : "Ab13(b9)"
                  }
               ]
            },
            {
               "chords" : [
                  {
                     "name" : "G7alt"
                  }
               ]
            },
            {
               "repeat_last" : 1
            },
            {
               "chords" : [
                  {
                     "name" : "Gb^7(#11)"
                  }
               ]
            },
            {
               "repeat_last" : 1
            },
            {
               "chords" : [
                  {
                     "name" : "Gbo7"
                  }
               ]
            },
            {
               "repeat_last" : 1
            },
            {
               "chords" : [
                  {
                     "beats" : 2,
                     "name" : "C/D(b)"
                  },
                  {
                     "beats" : 2,
                     "name" : "Bb/C"
                  }
               ]
            },
            {
               "chords" : [
                  {
                     "beats" : 2,
                     "name" : "C/B"
                  },
                  {
                     "beats" : 2,
                     "name" : "Bb-7"
                  }
               ]
            }
         ],
         "label" : "B"
      },
      {
         "bars" : [
            {
               "chords" : [
                  {
                     "name" : "A-9"
                  }
               ]
            },
            {
               "chords" : [
                  {
                     "name" : "E9sus"
                  }
               ],
               "comments" : [
                  "0-D.C. on cue"
               ]
            }
         ],
         "repeat" : 1,
         "description" : "Open"
      }
   ],
   "composer" : "Herbie Hancock",
   "key" : null
}
